homework/adder4/adder4.srcs/sources_1/new/adder4.v
`timescale 1ns / 1ps

module adder4(cout,sum,ina,inb,cin); 
    output[3:0] sum; 
    output cout; 
    input[3:0] ina,inb; 
    input cin; 
    assign {cout,sum}=ina+inb+cin; 
endmodule

homework/adder4/adder4.srcs/sim_1/new/test_adder4.v
 `timescale 1ns/1ns 
module test_adder4; 
wire[3:0] sum; 
wire cout; 
reg[3:0] ina,inb; 
reg cin; 
adder4 adder4_1(cout,sum,ina,inb,cin); 
initial begin 
#0 ina = 4'b0001; inb = 4'b1010; cin = 1'b0; 
#5 ina = 4'b0010; inb = 4'b1010; cin = 1'b1; 
#5 ina = 4'b0010; inb = 4'b1110; cin = 1'b0; 
#5 ina = 4'b0011; inb = 4'b1100; cin = 1'b1; 
#5 ina = 4'b0111; inb = 4'b1001; cin = 1'b0; 
#5 ina = 4'b0001; inb = 4'b1100; cin = 1'b1; 
#5 ina = 4'b0011; inb = 4'b1100; cin = 1'b0; 
#5 ina = 4'b0111; inb = 4'b1111; cin = 1'b1; 
#5 $finish; 
end 
initial 
$monitor("At time %t, ina(%b) + inb(%b) + cin(%b) = sum(%b)(%2d),cout(%b)",$time, ina, inb, cin, sum, sum, cout); 
initial 
begin 
$dumpfile("test.vcd"); 
$dumpvars(0,test_adder4); 
end 
endmodule

homework/adder4/adder4.sim/sim_1/behav/xsim/test.vcd
$date
   Sat Nov 30 18:50:26 2024
$end

$version
  2023.2
  $dumpfile ("test.vcd") 
$end

$timescale
  1ps
$end

$scope module test_adder4 $end
$var wire 4 ! sum [3:0] $end
$var wire 1 " cout $end
$var reg 4 # ina [3:0] $end
$var reg 4 $ inb [3:0] $end
$var reg 1 % cin $end
$scope module adder4_1 $end
$var wire 4 ! sum [3:0] $end
$var wire 1 " cout $end
$var wire 4 & ina [3:0] $end
$var wire 4 ' inb [3:0] $end
$var wire 1 ( cin $end
$upscope $end
$upscope $end
$enddefinitions $end

#0
$dumpvars
b1011 !
0"
b1 #
b1010 $
0%
b1 &
b1010 '
0(
$end

#5000
b1101 !
b10 #
1%
b10 &
1(

#10000
b0 !
1"
b1110 $
0%
b1110 '
0(

#15000
b11 #
b1100 $
1%
b11 &
b1100 '
1(

#20000
b111 #
b1001 $
0%
b111 &
b1001 '
0(

#25000
b1110 !
0"
b1 #
b1100 $
1%
b1 &
b1100 '
1(

#30000
b1111 !
b11 #
0%
b11 &
0(

#35000
b111 !
1"
b111 #
b1111 $
1%
b111 &
b1111 '
1(
